cScell
