Metadata-Version: 2.1
Name: cScell
Version: 1.0.2
Summary: A framework made with python for C cli projects
Home-page: https://github.com/euberdeveloper/cScell
Author: Eugenio Vinicio Berretta
Author-email: euberdeveloper@gmail.com
License: MIT
Download-URL: https://github.com/euberdeveloper/cScell/archive/v1.0.2.tar.gz
Keywords: cScell,shell,c,framework
Platform: UNKNOWN
Classifier: Development Status :: 5 - Production/Stable
Classifier: Intended Audience :: Developers
Classifier: Topic :: Software Development :: Build Tools
Classifier: License :: OSI Approved :: MIT License
Classifier: Programming Language :: Python :: 3.5
Classifier: Programming Language :: Python :: 3.6
Classifier: Programming Language :: Python :: 3.7
Classifier: Programming Language :: Python :: 3.8
